sed_extractor/__init__.py
sed_extractor/sed_extract.py
sed_extractor-1.3.0b15.dist-info/METADATA
sed_extractor-1.3.0b15.dist-info/WHEEL
sed_extractor-1.3.0b15.dist-info/licenses/LICENSE
sed_extractor-1.3.0b15.dist-info/RECORD
